cwitch/__init__.py
cwitch/__main__.py
cwitch/auto_completion.py
cwitch/cli.py
cwitch/config.py
cwitch/extractors.py
cwitch/input_validation.py
cwitch/printers.py
cwitch/prompts.py
cwitch/subcommands.py
cwitch-0.2.0.dist-info/LICENSE
cwitch-0.2.0.dist-info/METADATA
cwitch-0.2.0.dist-info/WHEEL
cwitch-0.2.0.dist-info/entry_points.txt
cwitch-0.2.0.dist-info/top_level.txt
cwitch-0.2.0.dist-info/RECORD
