Metadata-Version: 2.1
Name: cwitch
Version: 0.2.0
Summary: A CLI tool to watch Twitch live streams and videos.
Home-page: https://github.com/zer0-x/cwitch
Author: zer0-x
License: GPL-3.0
Project-URL: Issues, https://github.com/zer0-x/cwitch/issues
Project-URL: Changelog, https://github.com/zer0-x/cwitch/blob/main/CHANGELOG.md
Keywords: twitch,mpv,youtube-dl,stream,cli,live,video
Classifier: Environment :: Console
Classifier: Programming Language :: Python :: 3
Classifier: Intended Audience :: End Users/Desktop
Classifier: Topic :: Games/Entertainment
Classifier: Topic :: Internet
Classifier: License :: OSI Approved :: GNU General Public License v3 (GPLv3)
License-File: LICENSE
Requires-Dist: youtube-dl
Requires-Dist: python-mpv
Requires-Dist: prompt-toolkit
